cads_api_client/__init__.py
cads_api_client/api_client.py
cads_api_client/catalogue.py
cads_api_client/config.py
cads_api_client/legacy_api_client.py
cads_api_client/processing.py
cads_api_client/profile.py
cads_api_client/py.typed
cads_api_client/version.py
cads_api_client-1.5.4.dist-info/LICENSE
cads_api_client-1.5.4.dist-info/METADATA
cads_api_client-1.5.4.dist-info/WHEEL
cads_api_client-1.5.4.dist-info/top_level.txt
cads_api_client-1.5.4.dist-info/RECORD
